AUTHORS
LICENSE
MANIFEST.in
README.rst
setup.py
django_simple_feedback_collector.egg-info/PKG-INFO
django_simple_feedback_collector.egg-info/SOURCES.txt
django_simple_feedback_collector.egg-info/dependency_links.txt
django_simple_feedback_collector.egg-info/not-zip-safe
django_simple_feedback_collector.egg-info/top_level.txt
example_project/__init__.py
example_project/settings.py
example_project/urls.py
example_project/templates/demo.html
feedback/__init__.py
feedback/forms.py
feedback/models.py
feedback/urls.py
feedback/views.py
feedback/migrations/0001_initial.py
feedback/migrations/__init__.py
feedback/static/.DS_Store
feedback/static/feedback/.DS_Store
feedback/static/feedback/js/enable-feedback-api.js
feedback/tests/__init__.py
feedback/tests/forms.py
feedback/tests/models.py
feedback/tests/views.py