Metadata-Version: 1.1
Name: django-simple-feedback-collector
Version: 0.0.3
Summary: A simple feedback collector for Django
Home-page: UNKNOWN
Author: Ross Karchner
Author-email: ross.karchner@cfpb.gov
License: Public domain
Platform: UNKNOWN
Classifier: Topic :: Internet :: WWW/HTTP :: Dynamic Content
Classifier: Intended Audience :: Developers
Classifier: Programming Language :: Python
Classifier: Programming Language :: Python :: 2.6
Classifier: Programming Language :: Python :: 2.7
Classifier: Framework :: Django
Classifier: Development Status :: 4 - Beta
Classifier: Operating System :: OS Independent
